osenv/__init__.py
python_osenv-0.0.3.dist-info/WHEEL
python_osenv-0.0.3.dist-info/METADATA
python_osenv-0.0.3.dist-info/RECORD
